rdabase/__init__.py
rdabase/approxequal.py
rdabase/constants.py
rdabase/energy.py
rdabase/geoutils.py
rdabase/graph.py
rdabase/load.py
rdabase/misc.py
rdabase/population.py
rdabase/readwrite.py
rdabase/requireargs.py
rdabase/timers.py
rdabase/union_find.py
rdabase-2.6.0.dist-info/LICENSE
rdabase-2.6.0.dist-info/METADATA
rdabase-2.6.0.dist-info/WHEEL
rdabase-2.6.0.dist-info/top_level.txt
rdabase-2.6.0.dist-info/RECORD
