Metadata-Version: 2.1
Name: rdabase
Version: 2.6.0
Summary: Redistricting analytics data
Home-page: https://github.com/rdatools/rdabase
Author: alecramsay
Author-email: Alec Ramsay <a73cram5ay@gmail.com>
License: MIT
Project-URL: Homepage, https://github.com/rdatools/rdabase
Project-URL: Bug Tracker, https://github.com/rdatools/rdabase/issues
Classifier: Programming Language :: Python :: 3
Classifier: License :: OSI Approved :: MIT License
Classifier: Operating System :: OS Independent
Requires-Python: >=3.10
License-File: LICENSE
Requires-Dist: fiona
Requires-Dist: geopandas
Requires-Dist: libpysal
Requires-Dist: shapely
Requires-Dist: scipy
